Workbook

Sheet 00_readme_and_model_rules
A1: Stanley 1913 Financial Model
A2: Judge-defensible finance system | v01 | 2026-04-07
A4: Purpose | B4: This workbook supports Option 2 deep modeling, Option 1/3 light cases, scenario outputs, and judge-facing finance tables.
A5: Model philosophy | B5: Use consulting-case logic first: revenue, margin, investment, payback, scenario, and risk.
A6: Color legend | B6: Green = hard_fact | Yellow = derived_estimate | Orange = assumption
A7: Update rule | B7: If core inputs change materially, rerun 04_generate_finance_model_assets_v01.py to refresh scenario outputs and HTML appendix.
A8: Presentation rule | B8: Slides should use static conclusion tables. HTML appendix is supplemental and not required for the story to work.
A9: Current recommendation | B9: Option 2 remains the strongest risk-adjusted finance case.
A11: Class | B11: Meaning | C11: How to use
A12: hard_fact | B12: Directly disclosed by official company, government, SEC, or case exhibit | C12: Use directly in slides and backup
A13: derived_estimate | B13: Quantitative estimate triangulated from comparables or price architecture | C13: Use with source note and logic line
A14: assumption | B14: Management assumption required for forecasting | C14: Show explicitly and stress-test

Sheet 01_source_log
A1: Finance Source Log
A2: Only sources used directly in the finance model and appendix
A4: source_id | B4: title | C4: publisher | D4: type | E4: metric | F4: quant_label | G4: how_used | H4: url_or_path | I4: reliability
A5: LC01 | B5: MOSAIC Case Competition 2025-26 Case | C5: UW Foster MOSAIC | D5: local_case_pdf | E5: case_requirements | F5: n_a | G5: main case framing | H5: /Users/zhangziling/Documents/MSIS/Case comp_MOSAIC 2026/Case Competiton/MOSAIC Case Competition 2025-26 Case .pdf | I5: tier_1
A6: LC02 | B6: MCC 2025-26 Graduate Charge | C6: UW Foster MOSAIC | D6: local_case_pdf | E6: delivery_requirements | F6: n_a | G6: requirement matrix | H6: /Users/zhangziling/Documents/MSIS/Case comp_MOSAIC 2026/Case Competiton/MCC 2025-26 Graduate Charge.pdf | I6: tier_1
A7: LC08 | B7: MOSAIC 2026 48H Battle Checklist | C7: local_preparation_doc | D7: local_docx | E7: case_execution | F7: n_a | G7: internal readout | H7: /Users/zhangziling/Documents/MSIS/Case comp_MOSAIC 2026/MOSAIC_2026_48H_Battle_Checklist.docx | I7: tier_2
A8: LC09 | B8: Stanley 1913 Case Sources Industry Report and Option Analysis EN | C8: local_research_doc | D8: local_docx | E8: option_ranking | F8: n_a | G8: baseline synthesis | H8: /Users/zhangziling/Documents/MSIS/Case comp_MOSAIC 2026/Stanley_1913_Case_Sources_Industry_Report_and_Option_Analysis.docx | I8: tier_2
A9: LC10 | B9: Stanley 1913 Case Sources Industry Report and Option Analysis CN | C9: local_research_doc | D9: local_docx | E9: option_ranking | F9: n_a | G9: baseline synthesis | H9: /Users/zhangziling/Documents/MSIS/Case comp_MOSAIC 2026/Stanley_1913_Case_Sources_Industry_Report_and_Option_Analysis_CN.docx | I9: tier_2
A10: SC04 | B10: Vitalize Collection Launch | C10: Stanley 1913 | D10: official_company_news | E10: category_expansion | F10: n_a | G10: adjacency proof | H10: https://www.stanley1913.com/blogs/stanley-1913-newsroom/the-stanley-1913-brand-launches-new-vitalize%E2%84%A2-collection-featuring-totes-and-backpacks | I10: tier_1
A11: SC05 | B11: Adventure To-Go Food Jar 12 oz | C11: Stanley 1913 | D11: official_product_page | E11: product_assortment | F11: n_a | G11: product adjacency | H11: https://www.stanley1913.com/products/adventure-to-go-food-jar-12-oz | I11: tier_1
A12: SC06 | B12: All Day Mini Lunch Box | C12: Stanley 1913 | D12: official_product_page | E12: price_and_assortment | F12: 45_usd | G12: pricing benchmark | H12: https://www.stanley1913.com/products/midi-mini-lunch-boxes-4-qt | I12: tier_1
A13: SC09 | B13: Quencher 40 oz official search signal | C13: Stanley 1913 | D13: official_product_search_result | E13: price_point | F13: 45_usd | G13: pricing benchmark | H13: https://www.stanley1913.com/products/the-new-frequency-quencher-h20-flowstate-tumbler-40-oz?bvstate=pg%3A164%2Fct%3Ar&variant=44560341139583 | I13: tier_2
A14: SC10 | B14: Artisan Thermal Food Jar 27 oz official search signal | C14: Stanley 1913 | D14: official_product_search_result | E14: price_point | F14: 35_usd | G14: pricing benchmark | H14: https://www.stanley1913.com/products/artisan-thermal-food-jar-27-oz?bvstate=pg%3A2%2Fct%3Ar | I14: tier_2
A15: SC11 | B15: Hydro Flask Lunch Boxes | C15: Hydro Flask | D15: official_product_page | E15: price_ladder | F15: 39_95_and_59_95 | G15: peer price ladder | H15: https://www.hydroflask.com/shop/coolers/lunch-boxes | I15: tier_1
... A41: MC02 | B41: State of Consumer trends report 2025 | C41: McKinsey | D41: official_thought_leadership | E41: consumer_methodology_context | F41: 2838_consumers | G41: about research and consulting benchmark | H41: https://www.mckinsey.com/industries/consumer-packaged-goods/our-insights/state-of-consumer | I41: tier_1

Sheet 02_assumption_register
A1: Assumption Register
A2: All finance inputs classified as hard_fact, derived_estimate, or assumption
A4: sheet | B4: driver | C4: classification | D4: source_ids | E4: unit | F4: year_1 | G4: year_2 | H4: year_3 | I4: notes
A5: 03_stanley_baseline | B5: Current revenue anchor | C5: derived_estimate | D5: FM01 | E5: usd | F5: 750000000 | G5: 750000000 | H5: 750000000 | I5: Media-reported 2023 sales anchor for Year 0 scale context.
A6: 03_stanley_baseline | B6: Status quo revenue growth | C6: assumption | D6: LC09|LC10 | E6: percent | F6: 0.025 | G6: 0.025 | H6: 0.025 | I6: Moderate mature-brand growth assumption used only to show scale context.
A7: 03_stanley_baseline | B7: Global food storage market size | C7: hard_fact | D7: LC01 | E7: usd | F7: 173450000000 | G7: 173450000000 | H7: 173450000000 | I7: Case Exhibit D market size.
A8: 03_stanley_baseline | B8: Global food storage market CAGR | C8: hard_fact | D8: LC01 | E8: percent | F8: 0.046 | G8: 0.046 | H8: 0.046 | I8: Case Exhibit D projected 2025-2032 CAGR.
A9: 03_stanley_baseline | B9: APAC market share | C9: hard_fact | D9: LC01 | E9: percent | F9: 0.3676 | G9: 0.3676 | H9: 0.3676 | I9: Case industry overview regional market share.
A10: 03_stanley_baseline | B10: Reference premium-peer gross margin | C10: derived_estimate | D10: FC02|FC04|LC01 | E10: percent | F10: 0.57 | G10: 0.57 | H10: 0.57 | I10: Reference point for Stanley baseline economics based on premium peer set.
A11: 04_05_option_2_revenue | B11: SKU count | C11: assumption | D11: LC09|LC10|SC04|SC05|SC06 | E11: count | F11: 3 | G11: 5 | H11: 6 | I11: Platform starts with core meal system launch and expands selectively.
A12: 04_05_option_2_revenue | B12: Launch timing factor | C12: assumption | D12: LC02|EC04 | E12: factor | F12: 0.5 | G12: 0.85 | H12: 1 | I12: Half-year launch in Year 1, ramp-up in Year 2, full year from Year 3 onward.
A13: 04_05_option_2_revenue | B13: Units per SKU | C13: assumption | D13: LC09|LC10|EC06|EC07 | E13: units | F13: 180000 | G13: 220000 | H13: 260000 | I13: Conservative-to-moderate volume ramp for adjacent premium line.
A14: 04_05_option_2_revenue | B14: MSRP / ASP anchor | C14: derived_estimate | D14: SC06|SC09|SC10 | E14: usd | F14: 42 | G14: 43 | H14: 44 | I14: Anchored to current Stanley premium drinkware and foodware price ladder.
A15: 04_05_option_2_revenue | B15: DTC mix | C15: derived_estimate | D15: FC03|FC06|PC01|EC08|DC01 | E15: percent | F15: 0.52 | G15: 0.48 | H15: 0.44 | I15: Launch stays DTC-first versus public premium-peer channel mix, then broadens wholesale as the platform scales.
A16: 04_05_option_2_revenue | B16: Wholesale realization factor | C16: derived_estimate | D16: LC09|FC02|FC04 | E16: factor | F16: 0.68 | G16: 0.68 | H16: 0.68 | I16: Implied realized price vs. MSRP in partner channels.
... A47: 08_option_3_light_case | B47: Assortment adaptation cost | C47: assumption | D47: LC09|LC10 | E47: usd | F47: 7000000 | G47: 4000000 | H47: 2000000 | I47: Upfront product, messaging, and channel adaptation.

Sheet 03_stanley_baseline
A1: Stanley Baseline
A2: Baseline context used for scale, status quo bridge, and finance framing
A4: metric | B4: classification | C4: source_ids | D4: value | E4: unit | F4: logic
A5: Current revenue anchor | B5: derived_estimate | C5: FM01 | D5: 750000000 | E5: usd | F5: Media-reported 2023 sales anchor for Year 0 scale context.
A6: Status quo revenue growth | B6: assumption | C6: LC09|LC10 | D6: 0.025 | E6: percent | F6: Moderate mature-brand growth assumption used only to show scale context.
A7: Global food storage market size | B7: hard_fact | C7: LC01 | D7: 173450000000 | E7: usd | F7: Case Exhibit D market size.
A8: Global food storage market CAGR | B8: hard_fact | C8: LC01 | D8: 0.046 | E8: percent | F8: Case Exhibit D projected 2025-2032 CAGR.
A9: APAC market share | B9: hard_fact | C9: LC01 | D9: 0.3676 | E9: percent | F9: Case industry overview regional market share.
A10: Reference premium-peer gross margin | B10: derived_estimate | C10: FC02|FC04|LC01 | D10: 0.57 | E10: percent | F10: Reference point for Stanley baseline economics based on premium peer set.

Sheet 04_option_2_revenue_build
A1: Option 2 Revenue Build
A2: Driver-based revenue model for premium portable meal / foodware platform
A4: metric | B4: classification | C4: source_ids | D4: year_1 | E4: year_2 | F4: year_3 | G4: year_4 | H4: year_5 | I4: logic
A5: SKU count | B5: assumption | C5: LC09|LC10|SC04|SC05|SC06 | D5: 3 | E5: 5 | F5: 6 | G5: 7 | H5: 8 | I5: Platform starts with core meal system launch and expands selectively.
A6: Launch timing factor | B6: assumption | C6: LC02|EC04 | D6: 0.5 | E6: 0.85 | F6: 1 | G6: 1 | H6: 1 | I6: Half-year launch in Year 1, ramp-up in Year 2, full year from Year 3 onward.
A7: Units per SKU | B7: assumption | C7: LC09|LC10|EC06|EC07 | D7: 180000 | E7: 220000 | F7: 260000 | G7: 290000 | H7: 320000 | I7: Conservative-to-moderate volume ramp for adjacent premium line.
A8: MSRP / ASP anchor | B8: derived_estimate | C8: SC06|SC09|SC10 | D8: 42 | E8: 43 | F8: 44 | G8: 45 | H8: 46 | I8: Anchored to current Stanley premium drinkware and foodware price ladder.
A9: DTC mix | B9: derived_estimate | C9: FC03|FC06|PC01|EC08|DC01 | D9: 0.52 | E9: 0.48 | F9: 0.44 | G9: 0.4 | H9: 0.38 | I9: Launch stays DTC-first versus public premium-peer channel mix, then broadens wholesale as the platform scales.
A10: Wholesale realization factor | B10: derived_estimate | C10: LC09|FC02|FC04 | D10: 0.68 | E10: 0.68 | F10: 0.68 | G10: 0.68 | H10: 0.68 | I10: Implied realized price vs. MSRP in partner channels.
A11: Promo discount | B11: assumption | C11: EC06|EC07 | D11: 0.08 | E11: 0.07 | F11: 0.07 | G11: 0.06 | H11: 0.06 | I11: Modest promo support, improving as line matures.
A12: Returns rate | B12: assumption | C12: LC09|LC10 | D12: 0.03 | E12: 0.03 | F12: 0.025 | G12: 0.025 | H12: 0.025 | I12: Reasonable returns assumption for premium consumer hardgoods.
A13: Bundle penetration | B13: derived_estimate | C13: SC06|SC15|SC16|SC17|SC18|SC19|SC20 | D13: 0.12 | E13: 0.16 | F13: 0.2 | G13: 0.22 | H13: 0.24 | I13: Share of core orders that convert into a multi-component system purchase, anchored to official cross-sell and set design evidence.
A14: Attach rate | B14: assumption | C14: LC09|LC10|SC04 | D14: 0.9 | E14: 1 | F14: 1.05 | G14: 1.1 | H14: 1.15 | I14: Average attached item count when bundle behavior occurs.
A15: Attach ASP factor | B15: assumption | C15: SC05|SC06|SC09|SC10 | D15: 0.45 | E15: 0.45 | F15: 0.45 | G15: 0.45 | H15: 0.45 | I15: Attached item value as a share of core-line ASP.
A16: Gross units sold | B16: formula | D16: =D5*D6*D7 | E16: =E5*E6*E7 | F16: =F5*F6*F7 | G16: =G5*G6*G7 | H16: =H5*H6*H7 | I16: sku_count * launch_timing * units_per_sku
A17: DTC units | B17: formula | D17: =D16*D9 | E17: =E16*E9 | F17: =F16*F9 | G17: =G16*G9 | H17: =H16*H9 | I17: gross_units * dtc_mix
A18: Wholesale units | B18: formula | D18: =D16*(1-D9) | E18: =E16*(1-E9) | F18: =F16*(1-F9) | G18: =G16*(1-G9) | H18: =H16*(1-H9) | I18: gross_units * (1 - dtc_mix)
A19: Realized ASP DTC | B19: formula | D19: =D8*(1-D11)*(1-D12) | E19: =E8*(1-E11)*(1-E12) | F19: =F8*(1-F11)*(1-F12) | G19: =G8*(1-G11)*(1-G12) | H19: =H8*(1-H11)*(1-H12) | I19: asp * (1 - promo_discount) * (1 - returns)
A20: Realized ASP wholesale | B20: formula | D20: =D8*D10*(1-D12) | E20: =E8*E10*(1-E12) | F20: =F8*F10*(1-F12) | G20: =G8*G10*(1-G12) | H20: =H8*H10*(1-H12) | I20: asp * wholesale_realization * (1 - returns)
A21: Base sales | B21: formula | D21: =D17*D19+D18*D20 | E21: =E17*E19+E18*E20 | F21: =F17*F19+F18*F20 | G21: =G17*G19+G18*G20 | H21: =H17*H19+H18*H20 | I21: dtc_units * realized_asp_dtc + wholesale_units * realized_asp_wholesale
A22: Attached units | B22: formula | D22: =D16*D13*D14 | E22: =E16*E13*E14 | F22: =F16*F13*F14 | G22: =G16*G13*G14 | H22: =H16*H13*H14 | I22: gross_units * bundle_penetration * attach_rate
A23: Attach ASP | B23: formula | D23: =D8*D15 | E23: =E8*E15 | F23: =F8*F15 | G23: =G8*G15 | H23: =H8*H15 | I23: asp * attach_asp_factor
A24: Bundle sales | B24: formula | D24: =D22*D23 | E24: =E22*E23 | F24: =F22*F23 | G24: =G22*G23 | H24: =H22*H23 | I24: attached_units * attach_asp
A25: Net sales | B25: formula | D25: =D21+D24 | E25: =E21+E24 | F25: =F21+F24 | G25: =G21+G24 | H25: =H21+H24 | I25: base_sales + bundle_sales

Sheet 05_option_2_cost_build
A1: Option 2 Cost Build
A2: Gross margin, opex, and cash bridge for the recommended platform
A4: metric | B4: classification | C4: source_ids | D4: year_1 | E4: year_2 | F4: year_3 | G4: year_4 | H4: year_5 | I4: logic
A5: Unit COGS | B5: derived_estimate | C5: FC02|FC04|FC05 | D5: 10.5 | E5: 10.7 | F5: 10.9 | G5: 11.2 | H5: 11.5 | I5: Premium insulated foodware cost base anchored to peer margin range.
A6: Packaging per unit | B6: assumption | C6: MC01 | D6: 1.2 | E6: 1.2 | F6: 1.25 | G6: 1.25 | H6: 1.3 | I6: Premium packaging with sustainability-aware design choices.
A7: Freight per unit | B7: assumption | C7: FC01|LC01 | D7: 1.7 | E7: 1.6 | F7: 1.55 | G7: 1.5 | H7: 1.5 | I7: Landing costs improve modestly with scale and mix.
A8: Tariff load on manufacturing COGS | B8: derived_estimate | C8: FC01|LC01 | D8: 0.04 | E8: 0.04 | F8: 0.035 | G8: 0.035 | H8: 0.035 | I8: Partial exposure assumption rather than full tariff pass-through.
A9: Promo effect on gross margin | B9: assumption | C9: EC06|EC07 | D9: 0.01 | E9: 0.01 | F9: 0.009 | G9: 0.009 | H9: 0.008 | I9: Gross-margin drag from markdown and channel support.
A10: Launch marketing as % of sales | B10: derived_estimate | C10: FC02|FC04|FC06|FC07|DC01 | D10: 0.13 | E10: 0.12 | F10: 0.11 | G10: 0.1 | H10: 0.1 | I10: Front-loaded launch support kept inside public peer SG&A and reinvestment guardrails.
A11: Trade spend as % of sales | B11: assumption | C11: LC09|FC05 | D11: 0.05 | E11: 0.055 | F11: 0.06 | G11: 0.06 | H11: 0.06 | I11: Retail enablement and shelf support increases with scale.
A12: Incremental SG&A as % of sales | B12: assumption | C12: FC02|FC04|FC05|FC06|FC07 | D12: 0.04 | E12: 0.04 | F12: 0.042 | G12: 0.043 | H12: 0.044 | I12: Incremental commercial and support overhead for scaled platform.
A13: Design and tooling | B13: assumption | C13: LC09|LC10 | D13: 8000000 | E13: 4000000 | F13: 3000000 | G13: 2000000 | H13: 2000000 | I13: Front-loaded development and refresh cadence.
A14: Inventory support as % of sales | B14: derived_estimate | C14: FC03|FC04|FC06|FC07 | D14: 0.1 | E14: 0.098 | F14: 0.095 | G14: 0.093 | H14: 0.09 | I14: Inventory support is set below whole-company peers because the launch leverages Stanley's existing supply base, but it still charges explicit inventory build as the platform scales.
A15: Receivables support as % of sales | B15: derived_estimate | C15: FC04|FC07 | D15: 0.016 | E15: 0.018 | F15: 0.02 | G15: 0.022 | H15: 0.024 | I15: Receivables support starts low because the launch is DTC-first, then rises as wholesale mix expands.
A16: Payables offset as % of sales | B16: derived_estimate | C16: FC03|FC06|FC07 | D16: 0.038 | E16: 0.04 | F16: 0.041 | G16: 0.043 | H16: 0.045 | I16: Supplier terms offset part of the working-capital burden rather than forcing the model to fund inventory and receivables with no payables support.
A17: Capex if needed | B17: assumption | C17: LC09|LC10|FC06 | D17: 3000000 | E17: 2000000 | F17: 1500000 | G17: 1500000 | H17: 1500000 | I17: Light operations and systems support, not major manufacturing buildout.
A18: Total units incl. attached items | B18: formula | D18: ='04_option_2_revenue_build'!D16+'04_option_2_revenue_build'!D22 | E18: ='04_option_2_revenue_build'!E16+'04_option_2_revenue_build'!E22 | F18: ='04_option_2_revenue_build'!F16+'04_option_2_revenue_build'!F22 | G18: ='04_option_2_revenue_build'!G16+'04_option_2_revenue_build'!G22 | H18: ='04_option_2_revenue_build'!H16+'04_option_2_revenue_build'!H22 | I18: revenue units + attached units
A19: Manufacturing COGS | B19: formula | D19: =D18*D5 | E19: =E18*E5 | F19: =F18*F5 | G19: =G18*G5 | H19: =H18*H5 | I19: total_units * unit_cogs
A20: Packaging cost | B20: formula | D20: =D18*D6 | E20: =E18*E6 | F20: =F18*F6 | G20: =G18*G6 | H20: =H18*H6 | I20: total_units * packaging
A21: Freight cost | B21: formula | D21: =D18*D7 | E21: =E18*E7 | F21: =F18*F7 | G21: =G18*G7 | H21: =H18*H7 | I21: total_units * freight
A22: Tariff cost | B22: formula | D22: =D19*D8 | E22: =E19*E8 | F22: =F19*F8 | G22: =G19*G8 | H22: =H19*H8 | I22: manufacturing_cogs * tariff_load
A23: Promo effect cost | B23: formula | D23: ='04_option_2_revenue_build'!D25*D9 | E23: ='04_option_2_revenue_build'!E25*E9 | F23: ='04_option_2_revenue_build'!F25*F9 | G23: ='04_option_2_revenue_build'!G25*G9 | H23: ='04_option_2_revenue_build'!H25*H9 | I23: net_sales * promo_effect
A24: Total COGS | B24: formula | D24: =D19+D20+D21+D22+D23 | E24: =E19+E20+E21+E22+E23 | F24: =F19+F20+F21+F22+F23 | G24: =G19+G20+G21+G22+G23 | H24: =H19+H20+H21+H22+H23 | I24: sum cost components
A25: Gross profit | B25: formula | D25: ='04_option_2_revenue_build'!D25-D24 | E25: ='04_option_2_revenue_build'!E25-E24 | F25: ='04_option_2_revenue_build'!F25-F24 | G25: ='04_option_2_revenue_build'!G25-G24 | H25: ='04_option_2_revenue_build'!H25-H24 | I25: net_sales - total_cogs
A26: Gross margin | B26: formula | D26: =IF('04_option_2_revenue_build'!D25=0,0,D25/'04_option_2_revenue_build'!D25) | E26: =IF('04_option_2_revenue_build'!E25=0,0,E25/'04_option_2_revenue_build'!E25) | F26: =IF('04_option_2_revenue_build'!F25=0,0,F25/'04_option_2_revenue_build'!F25) | G26: =IF('04_option_2_revenue_build'!G25=0,0,G25/'04_option_2_revenue_build'!G25) | H26: =IF('04_option_2_revenue_build'!H25=0,0,H25/'04_option_2_revenue_build'!H25) | I26: gross_profit / net_sales
A27: Launch marketing $ | B27: formula | D27: ='04_option_2_revenue_build'!D25*D10 | E27: ='04_option_2_revenue_build'!E25*E10 | F27: ='04_option_2_revenue_build'!F25*F10 | G27: ='04_option_2_revenue_build'!G25*G10 | H27: ='04_option_2_revenue_build'!H25*H10 | I27: net_sales * launch_marketing
A28: Trade spend $ | B28: formula | D28: ='04_option_2_revenue_build'!D25*D11 | E28: ='04_option_2_revenue_build'!E25*E11 | F28: ='04_option_2_revenue_build'!F25*F11 | G28: ='04_option_2_revenue_build'!G25*G11 | H28: ='04_option_2_revenue_build'!H25*H11 | I28: net_sales * trade_spend
A29: Incremental SG&A $ | B29: formula | D29: ='04_option_2_revenue_build'!D25*D12 | E29: ='04_option_2_revenue_build'!E25*E12 | F29: ='04_option_2_revenue_build'!F25*F12 | G29: ='04_option_2_revenue_build'!G25*G12 | H29: ='04_option_2_revenue_build'!H25*H12 | I29: net_sales * incremental_sga
A30: Contribution profit | B30: formula | D30: =D25-D27-D28-D29 | E30: =E25-E27-E28-E29 | F30: =F25-F27-F28-F29 | G30: =G25-G27-G28-G29 | H30: =H25-H27-H28-H29 | I30: gross_profit - launch marketing - trade - SG&A
A31: Operating profit uplift | B31: formula | D31: =D30-D13 | E31: =E30-E13 | F31: =F30-F13 | G31: =G30-G13 | H31: =H30-H13 | I31: contribution profit - design and tooling
A32: Inventory support investment | B32: formula | D32: ='04_option_2_revenue_build'!D25*D14 | E32: ='04_option_2_revenue_build'!E25*E14 | F32: ='04_option_2_revenue_build'!F25*F14 | G32: ='04_option_2_revenue_build'!G25*G14 | H32: ='04_option_2_revenue_build'!H25*H14 | I32: net_sales * inventory support
A33: Receivables support investment | B33: formula | D33: ='04_option_2_revenue_build'!D25*D15 | E33: ='04_option_2_revenue_build'!E25*E15 | F33: ='04_option_2_revenue_build'!F25*F15 | G33: ='04_option_2_revenue_build'!G25*G15 | H33: ='04_option_2_revenue_build'!H25*H15 | I33: net_sales * receivables support
A34: Payables offset | B34: formula | D34: ='04_option_2_revenue_build'!D25*D16 | E34: ='04_option_2_revenue_build'!E25*E16 | F34: ='04_option_2_revenue_build'!F25*F16 | G34: ='04_option_2_revenue_build'!G25*G16 | H34: ='04_option_2_revenue_build'!H25*H16 | I34: net_sales * payables offset
A35: Working capital investment | B35: formula | D35: =D32+D33-D34 | E35: =E32+E33-E34 | F35: =F32+F33-F34 | G35: =G32+G33-G34 | H35: =H32+H33-H34 | I35: inventory + receivables - payables
A36: Net cash impact | B36: formula | D36: =D31-D35-D17 | E36: =E31-E35-E17 | F36: =F31-F35-F17 | G36: =G31-G35-G17 | H36: =H31-H35-H17 | I36: operating profit uplift - working capital - capex

Sheet 06_option_2_5yr_pnl
A1: Option 2 5-Year P&L
A2: Headline economics for deck and Q&A use
A4: metric | B4: classification | C4: source_ids | D4: year_1 | E4: year_2 | F4: year_3 | G4: year_4 | H4: year_5 | I4: logic
A5: Status quo revenue | B5: formula | C5: 03_stanley_baseline | D5: ='03_stanley_baseline'!D5*(1+'03_stanley_baseline'!D6) | E5: =D5*(1+'03_stanley_baseline'!D6) | F5: =E5*(1+'03_stanley_baseline'!D6) | G5: =F5*(1+'03_stanley_baseline'!D6) | H5: =G5*(1+'03_stanley_baseline'!D6) | I5: baseline anchor rolled forward
A6: Option 2 incremental sales | B6: formula | C6: 04_option_2_revenue_build | D6: ='04_option_2_revenue_build'!D25 | E6: ='04_option_2_revenue_build'!E25 | F6: ='04_option_2_revenue_build'!F25 | G6: ='04_option_2_revenue_build'!G25 | H6: ='04_option_2_revenue_build'!H25 | I6: net sales from revenue build
A7: Implied company revenue with Option 2 | B7: formula | C7: 06_option_2_5yr_pnl | D7: =D5+D6 | E7: =E5+E6 | F7: =F5+F6 | G7: =G5+G6 | H7: =H5+H6 | I7: status quo + incremental
A8: Incremental sales as % of status quo | B8: formula | C8: 06_option_2_5yr_pnl | D8: =IF(D5=0,0,D6/D5) | E8: =IF(E5=0,0,E6/E5) | F8: =IF(F5=0,0,F6/F5) | G8: =IF(G5=0,0,G6/G5) | H8: =IF(H5=0,0,H6/H5) | I8: incremental / status quo
A9: Gross profit | B9: formula | C9: 05_option_2_cost_build | D9: ='05_option_2_cost_build'!D23 | E9: ='05_option_2_cost_build'!E23 | F9: ='05_option_2_cost_build'!F23 | G9: ='05_option_2_cost_build'!G23 | H9: ='05_option_2_cost_build'!H23 | I9: from cost build
A10: Gross margin | B10: formula | C10: 05_option_2_cost_build | D10: ='05_option_2_cost_build'!D24 | E10: ='05_option_2_cost_build'!E24 | F10: ='05_option_2_cost_build'!F24 | G10: ='05_option_2_cost_build'!G24 | H10: ='05_option_2_cost_build'!H24 | I10: gross profit / net sales
A11: Operating profit uplift | B11: formula | C11: 05_option_2_cost_build | D11: ='05_option_2_cost_build'!D29 | E11: ='05_option_2_cost_build'!E29 | F11: ='05_option_2_cost_build'!F29 | G11: ='05_option_2_cost_build'!G29 | H11: ='05_option_2_cost_build'!H29 | I11: from cost build
A12: Net cash impact | B12: formula | C12: 05_option_2_cost_build | D12: ='05_option_2_cost_build'!D31 | E12: ='05_option_2_cost_build'!E31 | F12: ='05_option_2_cost_build'!F31 | G12: ='05_option_2_cost_build'!G31 | H12: ='05_option_2_cost_build'!H31 | I12: after working capital and capex
A13: Cumulative cash impact | B13: formula | C13: 06_option_2_5yr_pnl | D13: =D12 | E13: =D13+E12 | F13: =E13+F12 | G13: =F13+G12 | H13: =G13+H12 | I13: running cumulative
A15: Payback period (years) | D15: =IF(D13>=0,1,IF(E13>=0,2,IF(F13>=0,3,IF(G13>=0,4,IF(H13>=0,5,6)))))

Sheet 07_option_1_light_case
A1: Option 1 Light Case
A2: International expansion light model for comparison only
A4: metric | B4: classification | C4: source_ids | D4: year_1 | E4: year_2 | F4: year_3 | G4: year_4 | H4: year_5 | I4: logic
A5: Target premium market pool | B5: derived_estimate | C5: LC01|LC09 | D5: 1800000000 | E5: 2000000000 | F5: 2200000000 | G5: 2400000000 | H5: 2600000000 | I5: Single new-region premium adjacency pool.
A6: Entry ramp | B6: assumption | C6: LC01|LC02 | D6: 0.005 | E6: 0.012 | F6: 0.02 | G6: 0.03 | H6: 0.045 | I6: Slow scale due to distributor and market-entry friction.
A7: Local pricing factor | B7: assumption | C7: LC01|EC06 | D7: 0.95 | E7: 0.95 | F7: 0.96 | G7: 0.96 | H7: 0.97 | I7: Localized pricing relative to U.S. MSRP anchor.
A8: Distributor / partner take | B8: assumption | C8: LC01 | D8: 0.28 | E8: 0.28 | F8: 0.28 | G8: 0.28 | H8: 0.28 | I8: Partner margin and entry structure for new market.
A9: Contribution margin before tariff / FX | B9: derived_estimate | C9: FC02|FC04|FC05 | D9: 0.2 | E9: 0.22 | F9: 0.24 | G9: 0.25 | H9: 0.26 | I9: Pre-tariff margin potential in a premium new-market case.
A10: Tariff + FX load | B10: derived_estimate | C10: FC01 | D10: 0.08 | E10: 0.08 | F10: 0.07 | G10: 0.07 | H10: 0.06 | I10: Combined landed-cost and FX drag.
A11: Market entry cost | B11: assumption | C11: LC09|LC10 | D11: 18000000 | E11: 10000000 | F11: 7000000 | G11: 5000000 | H11: 4000000 | I11: Front-loaded investment in localization, partners, and market launch.
A12: Net sales | B12: formula | D12: =D5*D6*D7*(1-D8) | E12: =E5*E6*E7*(1-E8) | F12: =F5*F6*F7*(1-F8) | G12: =G5*G6*G7*(1-G8) | H12: =H5*H6*H7*(1-H8) | I12: target_market_size * entry_ramp * local_pricing * (1 - distributor_take)
A13: Operating margin % | B13: formula | D13: =D9-D10 | E13: =E9-E10 | F13: =F9-F10 | G13: =G9-G10 | H13: =H9-H10 | I13: contribution_margin - tariff_fx_load
A14: Operating profit | B14: formula | D14: =D12*D13-D11 | E14: =E12*E13-E11 | F14: =F12*F13-F11 | G14: =G12*G13-G11 | H14: =H12*H13-H11 | I14: net sales * operating margin - market entry cost
A15: Cumulative profit | B15: formula | D15: =D14 | E15: =D15+E14 | F15: =E15+F14 | G15: =F15+G14 | H15: =G15+H14 | I15: running cumulative
A16: Payback read | D16: =IF(D15>=0,1,IF(E15>=0,2,IF(F15>=0,3,IF(G15>=0,4,IF(H15>=0,5,">5")))))
A18: Top risks | B18: Top risks: tariff / FX volatility, distributor dependence, slower local demand build.

Sheet 08_option_3_light_case
A1: Option 3 Light Case
A2: New market segment light model for comparison only
A4: metric | B4: classification | C4: source_ids | D4: year_1 | E4: year_2 | F4: year_3 | G4: year_4 | H4: year_5 | I4: logic
A5: Target segment spend pool | B5: derived_estimate | C5: LC09|LC10|EC06|EC07 | D5: 850000000 | E5: 900000000 | F5: 960000000 | G5: 1020000000 | H5: 1080000000 | I5: Focused segment opportunity in existing markets.
A6: Segment penetration | B6: assumption | C6: LC09|LC10 | D6: 0.01 | E6: 0.018 | F6: 0.028 | G6: 0.038 | H6: 0.05 | I6: Share capture from sharpened segment focus.
A7: Conversion lift factor | B7: assumption | C7: EC06|EC07 | D7: 1.05 | E7: 1.06 | F7: 1.08 | G7: 1.09 | H7: 1.1 | I7: Improved conversion from tighter segment relevance.
A8: Marketing spend as % of sales | B8: derived_estimate | C8: FC02|FC04|FC05|DC01 | D8: 0.12 | E8: 0.11 | F8: 0.11 | G8: 0.1 | H8: 0.1 | I8: Higher early spend to build awareness in the segment, but still inside public peer reinvestment guardrails.
A9: Contribution margin before marketing | B9: derived_estimate | C9: FC02|FC04|FC05 | D9: 0.36 | E9: 0.37 | F9: 0.38 | G9: 0.38 | H9: 0.39 | I9: Higher contribution from leveraging existing footprint.
A10: Assortment adaptation cost | B10: assumption | C10: LC09|LC10 | D10: 7000000 | E10: 4000000 | F10: 2000000 | G10: 1500000 | H10: 1500000 | I10: Upfront product, messaging, and channel adaptation.
A11: Net sales | B11: formula | D11: =D5*D6*D7 | E11: =E5*E6*E7 | F11: =F5*F6*F7 | G11: =G5*G6*G7 | H11: =H5*H6*H7 | I11: target_segment_size * segment_penetration * conversion_lift
A12: Operating margin % | B12: formula | D12: =D9-D8 | E12: =E9-E8 | F12: =F9-F8 | G12: =G9-G8 | H12: =H9-H8 | I12: contribution_margin - marketing_spend
A13: Operating profit | B13: formula | D13: =D11*D12-D10 | E13: =E11*E12-E10 | F13: =F11*F12-F10 | G13: =G11*G12-G10 | H13: =H11*H12-H10 | I13: net sales * operating margin - assortment adaptation cost
A14: Cumulative profit | B14: formula | D14: =D13 | E14: =D14+E13 | F14: =E14+F13 | G14: =F14+G13 | H14: =G14+H13 | I14: running cumulative
A15: Payback read | D15: =IF(D14>=0,1,IF(E14>=0,2,IF(F14>=0,3,IF(G14>=0,4,IF(H14>=0,5,">5")))))
A17: Top risks | B17: Top risks: segment overlap with existing buyers, limited upside if product / channel change is too shallow.

Sheet 09_scenarios_and_sensitivity
A1: Scenarios And Sensitivity
A2: Base, upside, and pressure outputs for Option 2
A4: scenario | B4: year_5_net_sales | C4: year_5_gross_margin | D4: cumulative_cash | E4: payback_years | F4: units_multiplier | G4: bundle_delta | H4: tariff_delta | I4: marketing_delta
A5: Base | B5: 1.0404449e+08 | C5: 0.53040326 | D5: 45605414 | E5: 3 | F5: 1 | G5: 0 | H5: 0 | I5: 0
A6: Upside | B6: 1.2347012e+08 | C6: 0.54722938 | D6: 70734694 | E6: 3 | F6: 1.15 | G6: 0.03 | H6: -0.01 | I6: -0.01
A7: Pressure | B7: 88636822 | C7: 0.50550588 | D7: 22879505 | E7: 4 | F7: 0.88 | G7: -0.03 | H7: 0.02 | I7: 0.01
A10: sensitivity_test | B10: cumulative_cash | C10: delta_vs_base
A11: Units per SKU +10% | B11: 53015955 | C11: 7410541.4
A12: Unit COGS -5% | B12: 50842308 | C12: 5236894.6
A13: Tariff load -1.5pp | B13: 47122286 | C13: 1516871.9
A14: Bundle penetration +3pp | B14: 45609191 | C14: 3776.7705
A15: Bundle penetration -3pp | B15: 45601637 | C15: -3776.7705
A16: Tariff load +1.5pp | B16: 44088542 | C16: -1516871.9
A17: DTC mix -5.0pp | B17: 42681337 | C17: -2924076.3
A18: Unit COGS +5% | B18: 40368519 | C18: -5236894.6
A19: Inventory support +2.0pp | B19: 39871924 | C19: -5733489.8
A20: Units per SKU -10% | B20: 38194872 | C20: -7410541.4

Sheet 10_judge_output_tables
A1: Judge Output Tables
A2: Directly usable finance tables for slides, appendix, and Q&A
A4: option | B4: year_5_sales | C4: headline_margin | D4: upfront_investment | E4: cumulative_cash | F4: payback | G4: financial_read
A5: Option 2 | B5: 1.0404449e+08 | C5: 0.53040326 | D5: 11000000 | E5: 45605414 | F5: 3 | G5: Best mix of growth, margin resilience, and controllable execution.
A6: Option 1 | B6: 81712800 | C6: 0.2 | D6: 18000000 | E6: -10492352 | F6: >5 | G6: Large TAM but heavy entry cost and slower payback.
A7: Option 3 | B7: 59400000 | C7: 0.29 | D7: 7000000 | E7: 27500480 | F7: 3 | G7: Faster to test, but lower ceiling and weaker portfolio diversification.
A10: metric | B10: base | C10: upside | D10: pressure
A11: Year 5 net sales | B11: 1.0404449e+08 | C11: 1.2347012e+08 | D11: 88636822
A12: Year 5 gross margin | B12: 0.53040326 | C12: 0.54722938 | D12: 0.50550588
A13: 5-year cumulative cash | B13: 45605414 | C13: 70734694 | D13: 22879505
A14: Payback years | B14: 3 | C14: 3 | D14: 4
A17: first_year_kpi | B17: why_it_matters
A18: sell_through_rate | B18: Tests whether the line is resonating beyond initial hype.
A19: bundle_attach_rate | B19: Proves system behavior rather than single-SKU novelty.
A20: gross_margin | B20: Confirms premium pricing is surviving cost reality.
A21: return_rate | B21: Flags product-market fit or quality problems early.
A22: repeat_rate | B22: Shows whether the platform can become a habit and not a fad.
A23: dtc_mix | B23: Helps explain pricing quality and customer learning speed.

Sheet 11_qr_html_export_tables
A1: QR HTML Export Tables
A2: Values mirrored into the self-contained finance appendix HTML
A4: metric | B4: year_1 | C4: year_2 | D4: year_3 | E4: year_4 | F4: year_5 | G4: type | H4: source | I4: notes
A5: option_2_net_sales | B5: 9403763 | C5: 34093840 | D5: 59356440 | E5: 79775955 | F5: 1.0404449e+08 | G5: currency | H5: 04_option_2_revenue_build | I5: Base case revenue
A6: option_2_gross_margin | B6: 0.55034715 | C6: 0.5469197 | D6: 0.54319283 | E6: 0.53773171 | F6: 0.53040326 | G6: percent | H6: 05_option_2_cost_build | I6: Base case margin
A7: option_2_operating_profit | B7: -4893493.7 | C7: 7316417.2 | D7: 16658427 | E7: 24703542 | F7: 31960462 | G7: currency | H7: 05_option_2_cost_build | I7: Base case operating uplift
A8: option_2_dtc_mix | B8: 0.52 | C8: 0.48 | D8: 0.44 | E8: 0.4 | F8: 0.38 | G8: percent | H8: 04_option_2_revenue_build | I8: Channel-mix guardrail
A9: option_2_working_capital | B9: 733493.52 | C9: 2591131.8 | D9: 4392376.6 | E9: 5743868.8 | F9: 7179070 | G9: currency | H9: 05_option_2_cost_build | I9: Explicit working-capital support
A10: option_2_inventory_support | B10: 940376.3 | C10: 3341196.3 | D10: 5638861.8 | E10: 7419163.8 | F10: 9364004.4 | G10: currency | H10: 05_option_2_cost_build | I10: Inventory support component
A11: option_1_net_sales | B11: 6156000 | C11: 16416000 | D11: 30412800 | E11: 49766400 | F11: 81712800 | G11: currency | H11: 07_option_1_light_case | I11: Light-case revenue
A12: option_3_net_sales | B12: 8925000 | C12: 17172000 | D12: 29030400 | E12: 42248400 | F12: 59400000 | G12: currency | H12: 08_option_3_light_case | I12: Light-case revenue
A15: scenario | B15: year_5_net_sales | C15: year_5_gross_margin | D15: cumulative_cash | E15: payback_years
A16: Base | B16: 1.0404449e+08 | C16: 0.53040326 | D16: 45605414 | E16: 3
A17: Upside | B17: 1.2347012e+08 | C17: 0.54722938 | D17: 70734694 | E17: 3
A18: Pressure | B18: 88636822 | C18: 0.50550588 | D18: 22879505 | E18: 4
